CHANGES.rst
MANIFEST.in
README.rst
setup.py
Products/__init__.py
Products.Ienablesettrace.egg-info/PKG-INFO
Products.Ienablesettrace.egg-info/SOURCES.txt
Products.Ienablesettrace.egg-info/dependency_links.txt
Products.Ienablesettrace.egg-info/namespace_packages.txt
Products.Ienablesettrace.egg-info/not-zip-safe
Products.Ienablesettrace.egg-info/requires.txt
Products.Ienablesettrace.egg-info/top_level.txt
Products/Ienablesettrace/__init__.py
docs/LICENSE.txt