Metadata-Version: 1.1
Name: Products.Ienablesettrace
Version: 1.1.0
Summary: Fork of Products.enablesettrace which also allows import of ipdb in restricted code.
Home-page: http://github.com/collective/Products.Ienablesettrace
Author: Mark van Lent
Author-email: m.van.lent@zestsoftware.nl
License: ZPL 2.1
Keywords: Python Zope Plone skin script debugging
Platform: UNKNOWN
Classifier: Development Status :: 7 - Inactive
Classifier: Intended Audience :: Developers
Classifier: Framework :: Plone
Classifier: Framework :: Plone :: 4.3
Classifier: Framework :: Zope2
Classifier: Programming Language :: Python
Classifier: Programming Language :: Python :: 2.7
Classifier: Topic :: Software Development :: Libraries :: Python Modules
Classifier: License :: OSI Approved :: Zope Public License
